multipledispatch/__init__.py
multipledispatch/conflict.py
multipledispatch/core.py
multipledispatch/dispatcher.py
multipledispatch/utils.py
multipledispatch-0.5.0.dist-info/DESCRIPTION.rst
multipledispatch-0.5.0.dist-info/METADATA
multipledispatch-0.5.0.dist-info/RECORD
multipledispatch-0.5.0.dist-info/WHEEL
multipledispatch-0.5.0.dist-info/metadata.json
multipledispatch-0.5.0.dist-info/top_level.txt
