Metadata-Version: 1.0
Name: multipledispatch
Version: 0.5.0
Summary: Multiple dispatch
Home-page: http://github.com/mrocklin/multipledispatch/
Author: Matthew Rocklin
Author-email: mrocklin@gmail.com
License: BSD
Keywords: dispatch
Platform: UNKNOWN
